noted/noted.py
noted/lib/__init__.py
noted/lib/config.py
noted/lib/save.py
noted/lib/setup.py
noted_app-0.0.4.dist-info/METADATA
noted_app-0.0.4.dist-info/WHEEL
noted_app-0.0.4.dist-info/licenses/LICENSE
noted_app-0.0.4.dist-info/RECORD
