Metadata-Version: 2.4
Name: noted_app
Version: 0.0.4
Summary: A simple terminal app that manages your notes.
Project-URL: Homepage, https://github.com/joaoreboucas1/noted
Project-URL: Issues, https://github.com/joaoreboucas1/noted/issues
Author-email: João Rebouças <joao.reboucas1@gmail.com>
License-Expression: MIT
License-File: LICENSE
Classifier: Operating System :: Unix
Classifier: Programming Language :: Python :: 3
Requires-Python: >=3.8
